{
  "_comment": "Pages that pass AGENTS.md quality tests and are approved for Google indexing. All other pages will be noindex, nofollow and excluded from sitemap.",
  
  "tools": [
    "image-compressor",
    "bulk-image-resizer",
    "bulk-resizer",
    "image-resizer",
    "heic-to-jpg",
    "jpg-to-png",
    "png-to-jpg",
    "exif-remover",
    "crop-image",
    "image-redactor",
    "metadata-viewer",
    "image-upscaler"
  ],

  "articles": [
    "best-bulk-image-resizer-free",
    "best-free-image-resizer-online",
    "best-image-compressor-online",
    "how-to-remove-image-metadata",
    "how-to-convert-heic-to-jpg",
    "how-to-convert-png-to-jpg",
    "best-free-jpg-to-png-converter",
    "what-is-png",
    "what-is-webp",
    "image-compressor",
    "image-tools",
    "image-converter"
  ],

  "comparisons": [
    "avif-vs-jpg",
    "heic-vs-jpg",
    "webp-vs-svg",
    "png-vs-svg",
    "jpg-vs-tiff",
    "avif-vs-webp",
    "heic-vs-png",
    "jpg-vs-jpeg"
  ],

  "formats": [
    "png",
    "webp",
    "heic"
  ],

  "staticPages": [
    "/",
    "/compare/webp-vs-png",
    "/compare/webp-vs-jpg"
  ]
}
